upvest_cli/__init__.py
upvest_cli/__pkginfo__.py
upvest_cli/application.py
upvest_cli/config.py
upvest_cli/execute.py
upvest_cli/user.py
upvest_cli-0.5.dist-info/METADATA
upvest_cli-0.5.dist-info/WHEEL
upvest_cli-0.5.dist-info/entry_points.txt
upvest_cli-0.5.dist-info/top_level.txt
upvest_cli-0.5.dist-info/RECORD
