Metadata-Version: 2.1
Name: upvest-cli
Version: 0.5
Summary: Upvest CLI: CLI for using the Upvest CLI
Home-page: https://docs.upvest.co
Author: upvest.co
Author-email: tech@upvest.co
License: MIT
Keywords: upvest blockchain api cli
Platform: UNKNOWN
Classifier: Development Status :: 3 - Alpha
Classifier: Environment :: Console
Classifier: Intended Audience :: Developers
Classifier: Operating System :: OS Independent
Classifier: Topic :: Software Development
Classifier: Programming Language :: Python :: 3.6
Classifier: Programming Language :: Python :: 3.7
Classifier: Programming Language :: Python :: 3.8
Classifier: License :: OSI Approved :: MIT License
Requires-Dist: upvest (>=0.0.7)
Requires-Dist: PyYAML (>=5.1)
Provides-Extra: dev
Requires-Dist: pre-commit (==1.10.5) ; extra == 'dev'
Requires-Dist: prospector (==1.1.6.2) ; extra == 'dev'
